EnStp_de/EnStp_de.py
EnStp_de/__int__.py
EnStp_de-1.0.0.dist-info/METADATA
EnStp_de-1.0.0.dist-info/WHEEL
EnStp_de-1.0.0.dist-info/top_level.txt
EnStp_de-1.0.0.dist-info/RECORD
