Metadata-Version: 2.1
Name: EnStp-de
Version: 1.0.0
Summary: german stopwords for energy policy for content analysis based on LDA topic modeling
Author: Meixi Zhang
